Topsis_Shivom_101916036/__init__.py
Topsis_Shivom_101916036-0.0.0.dist-info/LICENSE
Topsis_Shivom_101916036-0.0.0.dist-info/METADATA
Topsis_Shivom_101916036-0.0.0.dist-info/WHEEL
Topsis_Shivom_101916036-0.0.0.dist-info/top_level.txt
Topsis_Shivom_101916036-0.0.0.dist-info/RECORD
