Metadata-Version: 2.1
Name: Topsis-Shivom-101916036
Version: 0.0.0
Summary: A small package to work with topsis
Home-page: https://github.com/shivom2k/Topsis-shivom-101916036
Author: Shivom Chawla
Author-email: shivomchawla2000@gmail.com
License: UNKNOWN
Platform: UNKNOWN
Classifier: Programming Language :: Python :: 3
Classifier: License :: OSI Approved :: MIT License
Classifier: Operating System :: OS Independent
License-File: LICENSE
